domcontext/__init__.py
domcontext/dom_context.py
domcontext/dom_node.py
domcontext/tokenizer.py
domcontext/_internal/__init__.py
domcontext/_internal/chunker/__init__.py
domcontext/_internal/chunker/atomic_serializers.py
domcontext/_internal/chunker/chunk.py
domcontext/_internal/chunker/chunker.py
domcontext/_internal/chunker/semantic_ir_serializer.py
domcontext/_internal/chunker/types.py
domcontext/_internal/filters/__init__.py
domcontext/_internal/filters/semantic_pass.py
domcontext/_internal/filters/visibility_pass.py
domcontext/_internal/filters/semantic/__init__.py
domcontext/_internal/filters/semantic/collapse_wrappers.py
domcontext/_internal/filters/semantic/convert.py
domcontext/_internal/filters/semantic/filter_attributes.py
domcontext/_internal/filters/semantic/filter_empty.py
domcontext/_internal/filters/semantic/generate_ids.py
domcontext/_internal/filters/visibility/__init__.py
domcontext/_internal/filters/visibility/css_hidden.py
domcontext/_internal/filters/visibility/non_visible_tags.py
domcontext/_internal/filters/visibility/utils.py
domcontext/_internal/filters/visibility/zero_dimensions.py
domcontext/_internal/ir/__init__.py
domcontext/_internal/ir/dom_ir.py
domcontext/_internal/ir/semantic_ir.py
domcontext/_internal/parsers/__init__.py
domcontext/_internal/parsers/cdp_parser.py
domcontext/_internal/parsers/html_parser.py
domcontext/utils/__init__.py
domcontext/utils/playwright.py
domcontext-0.1.3.dist-info/METADATA
domcontext-0.1.3.dist-info/WHEEL
domcontext-0.1.3.dist-info/top_level.txt
domcontext-0.1.3.dist-info/RECORD
