Metadata-Version: 2.1
Name: domcontext
Version: 0.1.3
Summary: Parse DOM trees into clean, LLM-friendly context
Author: Steve Wang
License: MIT
Project-URL: Homepage, https://github.com/steve-z-wang/domcontext
Project-URL: Repository, https://github.com/steve-z-wang/domcontext
Project-URL: Issues, https://github.com/steve-z-wang/domcontext/issues
Keywords: dom,html,llm,parsing,web,automation
Classifier: Development Status :: 3 - Alpha
Classifier: Intended Audience :: Developers
Classifier: License :: OSI Approved :: MIT License
Classifier: Programming Language :: Python :: 3
Classifier: Programming Language :: Python :: 3.8
Classifier: Programming Language :: Python :: 3.9
Classifier: Programming Language :: Python :: 3.10
Classifier: Programming Language :: Python :: 3.11
Classifier: Programming Language :: Python :: 3.12
Requires-Python: >=3.8
Requires-Dist: lxml>=4.9.0
Requires-Dist: tiktoken>=0.5.0
Provides-Extra: dev
Requires-Dist: pytest>=7.0.0; extra == "dev"
Requires-Dist: pytest-cov>=4.0.0; extra == "dev"
Requires-Dist: pytest-mock>=3.10.0; extra == "dev"
Requires-Dist: black>=23.0.0; extra == "dev"
Requires-Dist: ruff>=0.1.0; extra == "dev"
Provides-Extra: examples
Requires-Dist: jupyter>=1.0.0; extra == "examples"
Requires-Dist: notebook>=7.0.0; extra == "examples"
Provides-Extra: playwright
Requires-Dist: playwright>=1.40.0; extra == "playwright"
